{
    "progress": [
      {
        "userID": "12345",
        "percentageCompleted": 25,
        "streak": 5,
        "lessonsCompleted": [1],
        "quizzesCompleted": [1],
        "badgesEarned": ["First Lesson Completed"],
        "lastLessonDate": "2025-02-07",
        "leaderboardPosition": 10
      },
      {
        "userID": "67890",
        "percentageCompleted": 50,
        "streak": 10,
        "lessonsCompleted": [1, 2],
        "quizzesCompleted": [1, 2],
        "badgesEarned": ["First Lesson Completed", "Rhythm Master"],
        "lastLessonDate": "2025-02-06",
        "leaderboardPosition": 5
      }
    ]
  }
  